{
	"info": {
		"_postman_id": "609aa44a-d90b-483b-94a4-a4330ee1d740",
		"name": "pawan",
		"schema": "https://schema.getpostman.com/json/collection/v2.1.0/collection.json",
		"_exporter_id": "29487600"
	},
	"item": [
		{
			"name": "post",
			"request": {
				"method": "POST",
				"header": [],
				"body": {
					"mode": "raw",
					"raw": "{\r\n \"title\": \"We Urgently Need a New National COVID-19 Response Plan\",\r\n  \"link\": \"https://time.com/6142718/we-need-new-national-covid-19-response-plan/\"\r\n}",
					"options": {
						"raw": {
							"language": "json"
						}
					}
				},
				"url": {
					"raw": "http://localhost:8080/user/post",
					"protocol": "http",
					"host": [
						"localhost"
					],
					"port": "8080",
					"path": [
						"user",
						"post"
					]
				}
			},
			"response": []
		},
		{
			"name": "get",
			"request": {
				"method": "GET",
				"header": [],
				"url": {
					"raw": "http://localhost:8080/user/getAll",
					"protocol": "http",
					"host": [
						"localhost"
					],
					"port": "8080",
					"path": [
						"user",
						"getAll"
					]
				}
			},
			"response": []
		}
	]
}